nacos/__init__.py
nacos/client.py
nacos/commons.py
nacos/exception.py
nacos/files.py
nacos/params.py
nacos/timer.py
nacos/usage.py
nacos/utils.py
python_nacos-0.1.1.dist-info/LICENSE
python_nacos-0.1.1.dist-info/METADATA
python_nacos-0.1.1.dist-info/WHEEL
python_nacos-0.1.1.dist-info/top_level.txt
python_nacos-0.1.1.dist-info/RECORD
