Metadata-Version: 2.1
Name: python-nacos
Version: 0.1.1
Summary: Python3 client for Nacos.
Home-page: https://github.com/sunglowrise/python-nacos/
Maintainer: Murray
Maintainer-email: sunglowrise@qq.com
License: MIT
Download-URL: https://github.com/sunglowrise/python-nacos/
Keywords: nacos,python-nacos,pynacos,pynacos-sdk
Platform: Platform Independent
Classifier: Programming Language :: Python
Classifier: Intended Audience :: Developers
Classifier: Topic :: Software Development :: Libraries :: Python Modules
Classifier: Topic :: Internet :: WWW/HTTP :: Dynamic Content :: CGI Tools/Libraries
Classifier: Programming Language :: Python :: 3.6
Requires-Python: >=3.6
Requires-Dist: requests (>=2.22.0)
